{
    "description": "The best forum and archive on the internet for layman-friendly Q&A.", 
    "title": "Explain Like I'm Five | Don't Panic!", 
    "generated-utc": 1412344875, 
    "posts": [
        {
            "permalink": "http://www.reddit.com/r/explainlikeimfive/comments/2i5sqb/eli5_if_slaves_in_america_were_so_expensive_why/", 
            "domain": "self.explainlikeimfive", 
            "score": 922, 
            "nsfw": false, 
            "author": "theringinginmyears", 
            "url": "http://www.reddit.com/r/explainlikeimfive/comments/2i5sqb/eli5_if_slaves_in_america_were_so_expensive_why/", 
            "title": "ELI5: If slaves in America were so expensive, why were they beaten and killed?", 
            "id": "2i5sqb", 
            "created-utc": 1412310098.0, 
            "num-comments": 490
        }, 
        {
            "permalink": "http://www.reddit.com/r/explainlikeimfive/comments/2i55kl/eli5_why_does_disconnecting_and_reconnecting_to/", 
            "domain": "self.explainlikeimfive", 
            "score": 74, 
            "nsfw": false, 
            "author": "Biologistics", 
            "url": "http://www.reddit.com/r/explainlikeimfive/comments/2i55kl/eli5_why_does_disconnecting_and_reconnecting_to/", 
            "title": "ELI5: Why does disconnecting and reconnecting to my wifi seem to speed up my connection?", 
            "id": "2i55kl", 
            "created-utc": 1412295327.0, 
            "num-comments": 7
        }, 
        {
            "permalink": "http://www.reddit.com/r/explainlikeimfive/comments/2i5w2m/eli5_how_do_people_spray_paint_graffiti_on_top_of/", 
            "domain": "self.explainlikeimfive", 
            "score": 70, 
            "nsfw": false, 
            "author": "chrisdio6955", 
            "url": "http://www.reddit.com/r/explainlikeimfive/comments/2i5w2m/eli5_how_do_people_spray_paint_graffiti_on_top_of/", 
            "title": "ELI5: How do people spray paint graffiti on top of a overpass?", 
            "id": "2i5w2m", 
            "created-utc": 1412312795.0, 
            "num-comments": 31
        }, 
        {
            "permalink": "http://www.reddit.com/r/explainlikeimfive/comments/2i5iqc/eli5_ebola_information_post/", 
            "domain": "self.explainlikeimfive", 
            "score": 63, 
            "nsfw": false, 
            "author": "ACrusaderA", 
            "url": "http://www.reddit.com/r/explainlikeimfive/comments/2i5iqc/eli5_ebola_information_post/", 
            "title": "ELI5: Ebola Information Post.", 
            "id": "2i5iqc", 
            "created-utc": 1412303385.0, 
            "num-comments": 48
        }, 
        {
            "permalink": "http://www.reddit.com/r/explainlikeimfive/comments/2i40bc/eli5_how_does_groups_like_vice_get_interviews/", 
            "domain": "self.explainlikeimfive", 
            "score": 48, 
            "nsfw": false, 
            "author": "spellspoil", 
            "url": "http://www.reddit.com/r/explainlikeimfive/comments/2i40bc/eli5_how_does_groups_like_vice_get_interviews/", 
            "title": "ELI5: How does groups like Vice, get interviews with high profile criminals?", 
            "id": "2i40bc", 
            "created-utc": 1412272849.0, 
            "num-comments": 16
        }, 
        {
            "permalink": "http://www.reddit.com/r/explainlikeimfive/comments/2i65gu/eli5_why_does_the_american_government_only_have/", 
            "domain": "self.explainlikeimfive", 
            "score": 49, 
            "nsfw": false, 
            "author": "cupuz", 
            "url": "http://www.reddit.com/r/explainlikeimfive/comments/2i65gu/eli5_why_does_the_american_government_only_have/", 
            "title": "ELI5: Why does the american government only have two major parties?", 
            "id": "2i65gu", 
            "created-utc": 1412321895.0, 
            "num-comments": 23
        }, 
        {
            "permalink": "http://www.reddit.com/r/explainlikeimfive/comments/2i3c3p/eli5_why_are_calculator_numpads_vs_phone_numpads/", 
            "domain": "self.explainlikeimfive", 
            "score": 41, 
            "nsfw": false, 
            "author": "KeronCyst", 
            "url": "http://www.reddit.com/r/explainlikeimfive/comments/2i3c3p/eli5_why_are_calculator_numpads_vs_phone_numpads/", 
            "title": "ELI5: Why are calculator numpads vs. phone numpads vertically reversed in number order?", 
            "id": "2i3c3p", 
            "created-utc": 1412259887.0, 
            "num-comments": 11
        }, 
        {
            "permalink": "http://www.reddit.com/r/explainlikeimfive/comments/2i36ne/eli5_if_the_people_that_went_over_to_treat_ebola/", 
            "domain": "self.explainlikeimfive", 
            "score": 28, 
            "nsfw": false, 
            "author": "garrbear12", 
            "url": "http://www.reddit.com/r/explainlikeimfive/comments/2i36ne/eli5_if_the_people_that_went_over_to_treat_ebola/", 
            "title": "ELI5: If the people that went over to treat Ebola victims were wearing air tight suits to prevent them from getting the virus, how did they get Ebola?", 
            "id": "2i36ne", 
            "created-utc": 1412256617.0, 
            "num-comments": 20
        }, 
        {
            "permalink": "http://www.reddit.com/r/explainlikeimfive/comments/2i53t9/elif_what_causes_that_cramp_in_the_bottom_of_your/", 
            "domain": "self.explainlikeimfive", 
            "score": 22, 
            "nsfw": false, 
            "author": "DaRealNate", 
            "url": "http://www.reddit.com/r/explainlikeimfive/comments/2i53t9/elif_what_causes_that_cramp_in_the_bottom_of_your/", 
            "title": "ELIF: What causes that cramp in the bottom of your foot that happens out of no where and hurts like hell?", 
            "id": "2i53t9", 
            "created-utc": 1412294245.0, 
            "num-comments": 13
        }, 
        {
            "permalink": "http://www.reddit.com/r/explainlikeimfive/comments/2i5k9f/eli5_why_am_i_sometimes_so_tired_that_i_cant_sleep/", 
            "domain": "self.explainlikeimfive", 
            "score": 21, 
            "nsfw": false, 
            "author": "TheBra305", 
            "url": "http://www.reddit.com/r/explainlikeimfive/comments/2i5k9f/eli5_why_am_i_sometimes_so_tired_that_i_cant_sleep/", 
            "title": "ELI5: Why am I sometimes so tired that I can't sleep?", 
            "id": "2i5k9f", 
            "created-utc": 1412304345.0, 
            "num-comments": 7
        }, 
        {
            "permalink": "http://www.reddit.com/r/explainlikeimfive/comments/2i3fa8/eli5_how_do_colorless_pictures_from_the_1900s_and/", 
            "domain": "self.explainlikeimfive", 
            "score": 18, 
            "nsfw": false, 
            "author": "jazzedonyoface", 
            "url": "http://www.reddit.com/r/explainlikeimfive/comments/2i3fa8/eli5_how_do_colorless_pictures_from_the_1900s_and/", 
            "title": "ELI5: How do colorless pictures from the 1900s and below get an accurate colorization? How does one go about doing the transformation?", 
            "id": "2i3fa8", 
            "created-utc": 1412261702.0, 
            "num-comments": 14
        }, 
        {
            "permalink": "http://www.reddit.com/r/explainlikeimfive/comments/2i5wud/eli5_why_does_my_130_lb_boxerlab_mix_stay_off_the/", 
            "domain": "self.explainlikeimfive", 
            "score": 20, 
            "nsfw": false, 
            "author": "okgasman", 
            "url": "http://www.reddit.com/r/explainlikeimfive/comments/2i5wud/eli5_why_does_my_130_lb_boxerlab_mix_stay_off_the/", 
            "title": "ELI5: Why does my 130 lb boxer/lab mix stay off the bed she has been sleeping on for 6 years if there is a 1 lb 7 week old kitten on it?", 
            "id": "2i5wud", 
            "created-utc": 1412313434.0, 
            "num-comments": 12
        }, 
        {
            "permalink": "http://www.reddit.com/r/explainlikeimfive/comments/2i3qc0/eli5_what_is_physically_happening_that_causes_the/", 
            "domain": "self.explainlikeimfive", 
            "score": 17, 
            "nsfw": false, 
            "author": "nuraHx", 
            "url": "http://www.reddit.com/r/explainlikeimfive/comments/2i3qc0/eli5_what_is_physically_happening_that_causes_the/", 
            "title": "ELI5: What is physically happening that causes the inside of a cpu to heat up?", 
            "id": "2i3qc0", 
            "created-utc": 1412267685.0, 
            "num-comments": 20
        }, 
        {
            "permalink": "http://www.reddit.com/r/explainlikeimfive/comments/2i5r8e/eli5_how_is_it_legal_that_hooters_wont_let_men_be/", 
            "domain": "self.explainlikeimfive", 
            "score": 20, 
            "nsfw": false, 
            "author": "DiverGuy1982", 
            "url": "http://www.reddit.com/r/explainlikeimfive/comments/2i5r8e/eli5_how_is_it_legal_that_hooters_wont_let_men_be/", 
            "title": "ELI5: How is it legal that Hooters wont let men be waiters?", 
            "id": "2i5r8e", 
            "created-utc": 1412309006.0, 
            "num-comments": 35
        }, 
        {
            "permalink": "http://www.reddit.com/r/explainlikeimfive/comments/2i58si/eli5_why_does_getting_an_air_bubble_in_your/", 
            "domain": "self.explainlikeimfive", 
            "score": 16, 
            "nsfw": false, 
            "author": "mediocreMUFFIN", 
            "url": "http://www.reddit.com/r/explainlikeimfive/comments/2i58si/eli5_why_does_getting_an_air_bubble_in_your/", 
            "title": "ELI5: Why does getting an air bubble in your bloodstream kill you?", 
            "id": "2i58si", 
            "created-utc": 1412297315.0, 
            "num-comments": 23
        }, 
        {
            "permalink": "http://www.reddit.com/r/explainlikeimfive/comments/2i449n/eli5when_are_those_little_interviews_in_every/", 
            "domain": "self.explainlikeimfive", 
            "score": 18, 
            "nsfw": false, 
            "author": "rikkertt", 
            "url": "http://www.reddit.com/r/explainlikeimfive/comments/2i449n/eli5when_are_those_little_interviews_in_every/", 
            "title": "ELI5:When are those little interviews in every competitive show recorded?", 
            "id": "2i449n", 
            "created-utc": 1412274897.0, 
            "num-comments": 14
        }, 
        {
            "permalink": "http://www.reddit.com/r/explainlikeimfive/comments/2i3ro5/eli5if_thc_stays_in_your_system_for_so_long/", 
            "domain": "self.explainlikeimfive", 
            "score": 15, 
            "nsfw": false, 
            "author": "ihavebigtanks", 
            "url": "http://www.reddit.com/r/explainlikeimfive/comments/2i3ro5/eli5if_thc_stays_in_your_system_for_so_long/", 
            "title": "ELI5:If THC stays in your system for so long because its not water soluble like many other drugs, but it is soluble in alcohol, does that mean drinking liquor will remove THC from your body faster?", 
            "id": "2i3ro5", 
            "created-utc": 1412268409.0, 
            "num-comments": 9
        }, 
        {
            "permalink": "http://www.reddit.com/r/explainlikeimfive/comments/2i4x7y/eli5_is_all_military_equipment_emp_hardened_if/", 
            "domain": "self.explainlikeimfive", 
            "score": 14, 
            "nsfw": false, 
            "author": "IM_A_SOCK", 
            "url": "http://www.reddit.com/r/explainlikeimfive/comments/2i4x7y/eli5_is_all_military_equipment_emp_hardened_if/", 
            "title": "ELI5: Is all military equipment EMP hardened? If not couldn't an EMP drastically reduce a modern army's effectiveness?", 
            "id": "2i4x7y", 
            "created-utc": 1412290279.0, 
            "num-comments": 31
        }, 
        {
            "permalink": "http://www.reddit.com/r/explainlikeimfive/comments/2i3mwd/eli5_when_i_get_8_hours_of_sleep_i_wake_tired_and/", 
            "domain": "self.explainlikeimfive", 
            "score": 13, 
            "nsfw": false, 
            "author": "DabneyEatsIt", 
            "url": "http://www.reddit.com/r/explainlikeimfive/comments/2i3mwd/eli5_when_i_get_8_hours_of_sleep_i_wake_tired_and/", 
            "title": "ELI5: When I get 8+ hours of sleep, I wake tired and groggy but eventually \"wake up\" and am fine through the day. But when I get 5 or 6 hours of sleep, I wake ready for the day and am full of energy for about 2 hours then I crash. Why?", 
            "id": "2i3mwd", 
            "created-utc": 1412265890.0, 
            "num-comments": 14
        }, 
        {
            "permalink": "http://www.reddit.com/r/explainlikeimfive/comments/2i5er4/eli5_why_are_so_many_men_circumcised_when_it_is/", 
            "domain": "self.explainlikeimfive", 
            "score": 12, 
            "nsfw": false, 
            "author": "tellmealldemthings", 
            "url": "http://www.reddit.com/r/explainlikeimfive/comments/2i5er4/eli5_why_are_so_many_men_circumcised_when_it_is/", 
            "title": "ELI5: Why are so many men circumcised when it is not for a religious reason?", 
            "id": "2i5er4", 
            "created-utc": 1412300974.0, 
            "num-comments": 44
        }, 
        {
            "permalink": "http://www.reddit.com/r/explainlikeimfive/comments/2i3iqy/eli5_if_most_of_the_symptomsunpleasantness_of_the/", 
            "domain": "self.explainlikeimfive", 
            "score": 12, 
            "nsfw": false, 
            "author": "Callox", 
            "url": "http://www.reddit.com/r/explainlikeimfive/comments/2i3iqy/eli5_if_most_of_the_symptomsunpleasantness_of_the/", 
            "title": "ELI5: If most of the symptoms/unpleasantness of the common cold is actually my body's reaction to it, what damage is the actual virus doing to my body?", 
            "id": "2i3iqy", 
            "created-utc": 1412263601.0, 
            "num-comments": 8
        }, 
        {
            "permalink": "http://www.reddit.com/r/explainlikeimfive/comments/2i63zx/eli5_what_are_the_differences_between_blood_types/", 
            "domain": "self.explainlikeimfive", 
            "score": 12, 
            "nsfw": false, 
            "author": "jtwatts", 
            "url": "http://www.reddit.com/r/explainlikeimfive/comments/2i63zx/eli5_what_are_the_differences_between_blood_types/", 
            "title": "ELI5: What are the differences between blood types?", 
            "id": "2i63zx", 
            "created-utc": 1412320304.0, 
            "num-comments": 8
        }, 
        {
            "permalink": "http://www.reddit.com/r/explainlikeimfive/comments/2i5uwl/eli5_what_exactly_happens_chemically_that_causes/", 
            "domain": "self.explainlikeimfive", 
            "score": 12, 
            "nsfw": false, 
            "author": "511100", 
            "url": "http://www.reddit.com/r/explainlikeimfive/comments/2i5uwl/eli5_what_exactly_happens_chemically_that_causes/", 
            "title": "ELI5: What exactly happens chemically that causes your body temperature to rise when you're sick?", 
            "id": "2i5uwl", 
            "created-utc": 1412311817.0, 
            "num-comments": 5
        }, 
        {
            "permalink": "http://www.reddit.com/r/explainlikeimfive/comments/2i5rr9/eli5_where_do_deleted_files_go/", 
            "domain": "self.explainlikeimfive", 
            "score": 11, 
            "nsfw": false, 
            "author": "nopetorious", 
            "url": "http://www.reddit.com/r/explainlikeimfive/comments/2i5rr9/eli5_where_do_deleted_files_go/", 
            "title": "ELI5: Where do deleted files \"go\"?", 
            "id": "2i5rr9", 
            "created-utc": 1412309393.0, 
            "num-comments": 25
        }, 
        {
            "permalink": "http://www.reddit.com/r/explainlikeimfive/comments/2i5ztf/eli5_why_were_hops_ultimately_chosen_as_the_goto/", 
            "domain": "self.explainlikeimfive", 
            "score": 8, 
            "nsfw": false, 
            "author": "serenidade", 
            "url": "http://www.reddit.com/r/explainlikeimfive/comments/2i5ztf/eli5_why_were_hops_ultimately_chosen_as_the_goto/", 
            "title": "ELI5: Why were hops ultimately chosen as the go-to beer \"seasoning,\" now used almost exclusively instead of spice sachets, etc.?", 
            "id": "2i5ztf", 
            "created-utc": 1412316015.0, 
            "num-comments": 9
        }
    ], 
    "subreddit": "/r/explainlikeimfive/", 
    "expires-utc": 1412373600, 
    "reddit-url": "http://www.reddit.com/r/explainlikeimfive/", 
    "api-url": "http://daily.red/explain-like-i-am-five.json", 
    "display-name": "Explain Like I'm Five", 
    "order": 7
}