{
    "description": "The best forum and archive on the internet for layman-friendly Q&A.", 
    "title": "Explain Like I'm Five | Don't Panic!", 
    "generated-utc": 1412258476, 
    "posts": [
        {
            "permalink": "http://www.reddit.com/r/explainlikeimfive/comments/2i0ei0/eli5_why_does_breast_cancer_awareness_receive/", 
            "domain": "self.explainlikeimfive", 
            "score": 2534, 
            "nsfw": false, 
            "author": "down_vote_city__", 
            "url": "http://www.reddit.com/r/explainlikeimfive/comments/2i0ei0/eli5_why_does_breast_cancer_awareness_receive/", 
            "title": "ELI5: why does breast cancer awareness receive more marketing/funding/awareness than prostate cancer? 1 in 2 men will develop prostate cancer during his lifetime.", 
            "id": "2i0ei0", 
            "created-utc": 1412186043.0, 
            "num-comments": 2188
        }, 
        {
            "permalink": "http://www.reddit.com/r/explainlikeimfive/comments/2i00dp/eli5_what_is_happening_during_masturbation_or_sex/", 
            "domain": "self.explainlikeimfive", 
            "score": 516, 
            "nsfw": true, 
            "author": "frugalera", 
            "url": "http://www.reddit.com/r/explainlikeimfive/comments/2i00dp/eli5_what_is_happening_during_masturbation_or_sex/", 
            "title": "ELI5: What is happening during masturbation or sex when an orgasm is being \"built up?\"", 
            "id": "2i00dp", 
            "created-utc": 1412178824.0, 
            "num-comments": 92
        }, 
        {
            "permalink": "http://www.reddit.com/r/explainlikeimfive/comments/2hzya9/eli5_why_do_dogs_need_to_be_exercised_while_cats/", 
            "domain": "self.explainlikeimfive", 
            "score": 310, 
            "nsfw": false, 
            "author": "BelligerentGnu", 
            "url": "http://www.reddit.com/r/explainlikeimfive/comments/2hzya9/eli5_why_do_dogs_need_to_be_exercised_while_cats/", 
            "title": "ELI5: Why do dogs need to be exercised, while cats are fine on their own (and often sleep most of the day)?", 
            "id": "2hzya9", 
            "created-utc": 1412177698.0, 
            "num-comments": 143
        }, 
        {
            "permalink": "http://www.reddit.com/r/explainlikeimfive/comments/2hzn5c/eli5_how_does_sleep_deprivation_actually_kill_you/", 
            "domain": "self.explainlikeimfive", 
            "score": 204, 
            "nsfw": false, 
            "author": "MrSllew", 
            "url": "http://www.reddit.com/r/explainlikeimfive/comments/2hzn5c/eli5_how_does_sleep_deprivation_actually_kill_you/", 
            "title": "ELI5: How does sleep deprivation actually kill you?", 
            "id": "2hzn5c", 
            "created-utc": 1412171257.0, 
            "num-comments": 78
        }, 
        {
            "permalink": "http://www.reddit.com/r/explainlikeimfive/comments/2i08ct/eli5sharia_law/", 
            "domain": "self.explainlikeimfive", 
            "score": 153, 
            "nsfw": false, 
            "author": "zorbada", 
            "url": "http://www.reddit.com/r/explainlikeimfive/comments/2i08ct/eli5sharia_law/", 
            "title": "ELI5:Sharia Law", 
            "id": "2i08ct", 
            "created-utc": 1412183002.0, 
            "num-comments": 184
        }, 
        {
            "permalink": "http://www.reddit.com/r/explainlikeimfive/comments/2hzvm1/eli5_if_our_body_is_constantly_producing_new/", 
            "domain": "self.explainlikeimfive", 
            "score": 143, 
            "nsfw": false, 
            "author": "theyak93", 
            "url": "http://www.reddit.com/r/explainlikeimfive/comments/2hzvm1/eli5_if_our_body_is_constantly_producing_new/", 
            "title": "ELI5 If our body is constantly producing new cells to replace old ones, why do we age?", 
            "id": "2hzvm1", 
            "created-utc": 1412176253.0, 
            "num-comments": 99
        }, 
        {
            "permalink": "http://www.reddit.com/r/explainlikeimfive/comments/2i0d1c/eli5_whats_the_difference_between_decriminalizing/", 
            "domain": "self.explainlikeimfive", 
            "score": 102, 
            "nsfw": false, 
            "author": "Wesspeaks", 
            "url": "http://www.reddit.com/r/explainlikeimfive/comments/2i0d1c/eli5_whats_the_difference_between_decriminalizing/", 
            "title": "ELI5: What's the difference between decriminalizing something and just making it legal?", 
            "id": "2i0d1c", 
            "created-utc": 1412185335.0, 
            "num-comments": 25
        }, 
        {
            "permalink": "http://www.reddit.com/r/explainlikeimfive/comments/2hzkx2/eli5reddit_stockchanges/", 
            "domain": "self.explainlikeimfive", 
            "score": 100, 
            "nsfw": false, 
            "author": "TomMorrow2", 
            "url": "http://www.reddit.com/r/explainlikeimfive/comments/2hzkx2/eli5reddit_stockchanges/", 
            "title": "ELI5-Reddit Stock/changes", 
            "id": "2hzkx2", 
            "created-utc": 1412169775.0, 
            "num-comments": 17
        }, 
        {
            "permalink": "http://www.reddit.com/r/explainlikeimfive/comments/2hzz2i/eli5_html5_gifs/", 
            "domain": "self.explainlikeimfive", 
            "score": 83, 
            "nsfw": false, 
            "author": "Theoduin", 
            "url": "http://www.reddit.com/r/explainlikeimfive/comments/2hzz2i/eli5_html5_gifs/", 
            "title": "ELI5: HTML5 GIFs", 
            "id": "2hzz2i", 
            "created-utc": 1412178119.0, 
            "num-comments": 42
        }, 
        {
            "permalink": "http://www.reddit.com/r/explainlikeimfive/comments/2hzr06/eli5_why_do_i_find_other_people_more_attractive/", 
            "domain": "self.explainlikeimfive", 
            "score": 79, 
            "nsfw": false, 
            "author": "GabeNewellHalfLife", 
            "url": "http://www.reddit.com/r/explainlikeimfive/comments/2hzr06/eli5_why_do_i_find_other_people_more_attractive/", 
            "title": "ELI5: Why do I find other people more attractive in clothing than when they are naked?", 
            "id": "2hzr06", 
            "created-utc": 1412173615.0, 
            "num-comments": 21
        }, 
        {
            "permalink": "http://www.reddit.com/r/explainlikeimfive/comments/2hzq0e/eli5why_do_countries_like_the_us_and_canada_have/", 
            "domain": "self.explainlikeimfive", 
            "score": 74, 
            "nsfw": false, 
            "author": "inquisitiveanon", 
            "url": "http://www.reddit.com/r/explainlikeimfive/comments/2hzq0e/eli5why_do_countries_like_the_us_and_canada_have/", 
            "title": "ELI5:Why do countries like the US and Canada have civilian flights available to Ebola infected countries like Liberia?", 
            "id": "2hzq0e", 
            "created-utc": 1412173023.0, 
            "num-comments": 31
        }, 
        {
            "permalink": "http://www.reddit.com/r/explainlikeimfive/comments/2i01rc/eli5_why_do_photographs_look_so_hideously_wrong/", 
            "domain": "self.explainlikeimfive", 
            "score": 71, 
            "nsfw": false, 
            "author": "Zxndy", 
            "url": "http://www.reddit.com/r/explainlikeimfive/comments/2i01rc/eli5_why_do_photographs_look_so_hideously_wrong/", 
            "title": "ELI5: Why do photographs look so hideously wrong when 'flipped'?", 
            "id": "2i01rc", 
            "created-utc": 1412179513.0, 
            "num-comments": 17
        }, 
        {
            "permalink": "http://www.reddit.com/r/explainlikeimfive/comments/2hzvny/eli5_why_does_the_urge_to_use_the_bathroom/", 
            "domain": "self.explainlikeimfive", 
            "score": 68, 
            "nsfw": false, 
            "author": "YappasOnDeck", 
            "url": "http://www.reddit.com/r/explainlikeimfive/comments/2hzvny/eli5_why_does_the_urge_to_use_the_bathroom/", 
            "title": "ELI5: Why does the urge to use the bathroom increase by about 1000% as soon as I walk in a bathroom?", 
            "id": "2hzvny", 
            "created-utc": 1412176289.0, 
            "num-comments": 39
        }, 
        {
            "permalink": "http://www.reddit.com/r/explainlikeimfive/comments/2hzoyn/eli5_what_good_is_there_in_consuming_vitamins_in/", 
            "domain": "self.explainlikeimfive", 
            "score": 63, 
            "nsfw": false, 
            "author": "savagebyname", 
            "url": "http://www.reddit.com/r/explainlikeimfive/comments/2hzoyn/eli5_what_good_is_there_in_consuming_vitamins_in/", 
            "title": "ELI5: What good is there in consuming vitamins in quantities many times more than in the RDA and does your body process the sudden excess in a productive way?", 
            "id": "2hzoyn", 
            "created-utc": 1412172346.0, 
            "num-comments": 42
        }, 
        {
            "permalink": "http://www.reddit.com/r/explainlikeimfive/comments/2hzwhu/eli5_how_the_sugar_frosting_on_a_poptart_doesnt/", 
            "domain": "self.explainlikeimfive", 
            "score": 51, 
            "nsfw": false, 
            "author": "ducttapetoiletpaper", 
            "url": "http://www.reddit.com/r/explainlikeimfive/comments/2hzwhu/eli5_how_the_sugar_frosting_on_a_poptart_doesnt/", 
            "title": "ELI5: How the sugar frosting on a pop-tart doesn't melt in the toaster.", 
            "id": "2hzwhu", 
            "created-utc": 1412176740.0, 
            "num-comments": 5
        }, 
        {
            "permalink": "http://www.reddit.com/r/explainlikeimfive/comments/2hzx59/eli5_how_exactly_did_trench_warfare_during_the/", 
            "domain": "self.explainlikeimfive", 
            "score": 53, 
            "nsfw": false, 
            "author": "ms15710", 
            "url": "http://www.reddit.com/r/explainlikeimfive/comments/2hzx59/eli5_how_exactly_did_trench_warfare_during_the/", 
            "title": "ELI5: How exactly did Trench Warfare during the First World War work?", 
            "id": "2hzx59", 
            "created-utc": 1412177085.0, 
            "num-comments": 42
        }, 
        {
            "permalink": "http://www.reddit.com/r/explainlikeimfive/comments/2hzldv/eli5_if_i_were_to_go_back_in_time_would_a/", 
            "domain": "self.explainlikeimfive", 
            "score": 47, 
            "nsfw": false, 
            "author": "jackson_hines", 
            "url": "http://www.reddit.com/r/explainlikeimfive/comments/2hzldv/eli5_if_i_were_to_go_back_in_time_would_a/", 
            "title": "ELI5: If I were to go back in time, would a randomly generated event still have the same outcome?", 
            "id": "2hzldv", 
            "created-utc": 1412170094.0, 
            "num-comments": 22
        }, 
        {
            "permalink": "http://www.reddit.com/r/explainlikeimfive/comments/2hzr8t/eli5_how_antarctica_can_exports_over_3_million/", 
            "domain": "self.explainlikeimfive", 
            "score": 51, 
            "nsfw": false, 
            "author": "IAmCacao", 
            "url": "http://www.reddit.com/r/explainlikeimfive/comments/2hzr8t/eli5_how_antarctica_can_exports_over_3_million/", 
            "title": "ELI5: How Antarctica can exports over 3 million $ worth of telephones (among many other exotic stuff) every year when it has no permanent residents?", 
            "id": "2hzr8t", 
            "created-utc": 1412173747.0, 
            "num-comments": 17
        }, 
        {
            "permalink": "http://www.reddit.com/r/explainlikeimfive/comments/2i05m9/eli5_if_you_can_use_alcohol_to_clean_wounds_from/", 
            "domain": "self.explainlikeimfive", 
            "score": 34, 
            "nsfw": false, 
            "author": "RobinLv", 
            "url": "http://www.reddit.com/r/explainlikeimfive/comments/2i05m9/eli5_if_you_can_use_alcohol_to_clean_wounds_from/", 
            "title": "ELI5: If you can use alcohol to clean wounds from infection, can you cure yourself by getting drunk while sick?", 
            "id": "2i05m9", 
            "created-utc": 1412181535.0, 
            "num-comments": 61
        }, 
        {
            "permalink": "http://www.reddit.com/r/explainlikeimfive/comments/2hzmtt/eli5_why_do_some_hair_colours_not_occur_naturally/", 
            "domain": "self.explainlikeimfive", 
            "score": 25, 
            "nsfw": false, 
            "author": "Gaben1231", 
            "url": "http://www.reddit.com/r/explainlikeimfive/comments/2hzmtt/eli5_why_do_some_hair_colours_not_occur_naturally/", 
            "title": "ELI5: Why do some hair colours not occur naturally? e.g Blue.", 
            "id": "2hzmtt", 
            "created-utc": 1412171038.0, 
            "num-comments": 28
        }, 
        {
            "permalink": "http://www.reddit.com/r/explainlikeimfive/comments/2hzyqe/eli5_why_did_the_bbc_suddenly_decide_to_up_and/", 
            "domain": "self.explainlikeimfive", 
            "score": 24, 
            "nsfw": false, 
            "author": "Beccorban", 
            "url": "http://www.reddit.com/r/explainlikeimfive/comments/2hzyqe/eli5_why_did_the_bbc_suddenly_decide_to_up_and/", 
            "title": "ELI5: Why did the BBC suddenly decide to up and move to Manchester?", 
            "id": "2hzyqe", 
            "created-utc": 1412177932.0, 
            "num-comments": 23
        }, 
        {
            "permalink": "http://www.reddit.com/r/explainlikeimfive/comments/2i2aw8/eli5_if_people_can_build_their_own_computers_what/", 
            "domain": "self.explainlikeimfive", 
            "score": 30, 
            "nsfw": false, 
            "author": "nmb8443", 
            "url": "http://www.reddit.com/r/explainlikeimfive/comments/2i2aw8/eli5_if_people_can_build_their_own_computers_what/", 
            "title": "ELI5: If people can build their own computers, what is stopping people from building their own smartphones?", 
            "id": "2i2aw8", 
            "created-utc": 1412224806.0, 
            "num-comments": 38
        }, 
        {
            "permalink": "http://www.reddit.com/r/explainlikeimfive/comments/2i0ei5/eli5_how_will_our_planets_water_levels_rise_when/", 
            "domain": "self.explainlikeimfive", 
            "score": 23, 
            "nsfw": false, 
            "author": "LoLBrotastic", 
            "url": "http://www.reddit.com/r/explainlikeimfive/comments/2i0ei5/eli5_how_will_our_planets_water_levels_rise_when/", 
            "title": "ELI5: How will our planets water levels rise when the ice melts but a glass of ice water doesn't over flow when the ice melts?", 
            "id": "2i0ei5", 
            "created-utc": 1412186046.0, 
            "num-comments": 35
        }, 
        {
            "permalink": "http://www.reddit.com/r/explainlikeimfive/comments/2i0kq8/eli5_why_the_new_microsoft_operating_system_is/", 
            "domain": "self.explainlikeimfive", 
            "score": 18, 
            "nsfw": false, 
            "author": "shortcrazy", 
            "url": "http://www.reddit.com/r/explainlikeimfive/comments/2i0kq8/eli5_why_the_new_microsoft_operating_system_is/", 
            "title": "ELI5: Why the new Microsoft operating system is called Windows 10 and not Windows 9", 
            "id": "2i0kq8", 
            "created-utc": 1412189068.0, 
            "num-comments": 20
        }, 
        {
            "permalink": "http://www.reddit.com/r/explainlikeimfive/comments/2hzmqf/eli5_when_i_have_a_small_cut_sore_or_bruise_why/", 
            "domain": "self.explainlikeimfive", 
            "score": 14, 
            "nsfw": false, 
            "author": "DonkeyBONEZ", 
            "url": "http://www.reddit.com/r/explainlikeimfive/comments/2hzmqf/eli5_when_i_have_a_small_cut_sore_or_bruise_why/", 
            "title": "ELI5: When I have a small cut, sore or bruise why do I have the urge to poke at it?", 
            "id": "2hzmqf", 
            "created-utc": 1412170971.0, 
            "num-comments": 3
        }
    ], 
    "subreddit": "/r/explainlikeimfive/", 
    "expires-utc": 1412287200, 
    "reddit-url": "http://www.reddit.com/r/explainlikeimfive/", 
    "api-url": "http://daily.red/explain-like-i-am-five.json", 
    "display-name": "Explain Like I'm Five", 
    "order": 7
}