{
    "category": "Knowledge", 
    "description": "Tips that improve your life in one way or another", 
    "title": "Life Pro Tips", 
    "generated-utc": 1411941676, 
    "posts": [
        {
            "num-comments": 177, 
            "domain": "self.LifeProTips", 
            "score": 1526, 
            "nsfw": false, 
            "title": "LPT: when you are paywalled out of an article that you accessed through the New York Times website, just google the title of that article and read it for free.", 
            "url": "http://www.reddit.com/r/LifeProTips/comments/2hncqp/lpt_when_you_are_paywalled_out_of_an_article_that/", 
            "author": "allthecatsintheworld", 
            "permalink": "http://www.reddit.com/r/LifeProTips/comments/2hncqp/lpt_when_you_are_paywalled_out_of_an_article_that/", 
            "created-utc": 1411854475.0, 
            "id": "2hncqp"
        }, 
        {
            "num-comments": 95, 
            "domain": "self.LifeProTips", 
            "score": 617, 
            "nsfw": false, 
            "title": "LPT Request: Speaking to recruiters at job fairs", 
            "url": "http://www.reddit.com/r/LifeProTips/comments/2hp44o/lpt_request_speaking_to_recruiters_at_job_fairs/", 
            "author": "justhereforhides", 
            "permalink": "http://www.reddit.com/r/LifeProTips/comments/2hp44o/lpt_request_speaking_to_recruiters_at_job_fairs/", 
            "created-utc": 1411912926.0, 
            "id": "2hp44o"
        }, 
        {
            "num-comments": 45, 
            "domain": "self.LifeProTips", 
            "score": 142, 
            "nsfw": false, 
            "title": "LPT request: How to comfort a sad person", 
            "url": "http://www.reddit.com/r/LifeProTips/comments/2hnwmf/lpt_request_how_to_comfort_a_sad_person/", 
            "author": "Vindria", 
            "permalink": "http://www.reddit.com/r/LifeProTips/comments/2hnwmf/lpt_request_how_to_comfort_a_sad_person/", 
            "created-utc": 1411868525.0, 
            "id": "2hnwmf"
        }, 
        {
            "num-comments": 10, 
            "domain": "self.LifeProTips", 
            "score": 68, 
            "nsfw": false, 
            "title": "LPT: When trying to get the attention of a large, noisy group in a room and raising your voice is ineffective, just turn off the lights.", 
            "url": "http://www.reddit.com/r/LifeProTips/comments/2hnzw4/lpt_when_trying_to_get_the_attention_of_a_large/", 
            "author": "schlong_thong", 
            "permalink": "http://www.reddit.com/r/LifeProTips/comments/2hnzw4/lpt_when_trying_to_get_the_attention_of_a_large/", 
            "created-utc": 1411870972.0, 
            "id": "2hnzw4"
        }, 
        {
            "num-comments": 3, 
            "domain": "self.LifeProTips", 
            "score": 39, 
            "nsfw": false, 
            "title": "LPT: A list of alternate domains that point to @mailinator.com", 
            "url": "http://www.reddit.com/r/LifeProTips/comments/2hovnq/lpt_a_list_of_alternate_domains_that_point_to/", 
            "author": "nocturnalgeek", 
            "permalink": "http://www.reddit.com/r/LifeProTips/comments/2hovnq/lpt_a_list_of_alternate_domains_that_point_to/", 
            "created-utc": 1411904460.0, 
            "id": "2hovnq"
        }, 
        {
            "num-comments": 15, 
            "domain": "self.LifeProTips", 
            "score": 43, 
            "nsfw": false, 
            "title": "LPT Request: How to get the sour milk smell out of a travel mug?", 
            "url": "http://www.reddit.com/r/LifeProTips/comments/2hpkgc/lpt_request_how_to_get_the_sour_milk_smell_out_of/", 
            "author": "spiderfanmail", 
            "permalink": "http://www.reddit.com/r/LifeProTips/comments/2hpkgc/lpt_request_how_to_get_the_sour_milk_smell_out_of/", 
            "created-utc": 1411924115.0, 
            "id": "2hpkgc"
        }, 
        {
            "num-comments": 7, 
            "domain": "self.LifeProTips", 
            "score": 20, 
            "nsfw": false, 
            "title": "LPT: Study a map of a different place in the world each day, for fifteen minutes", 
            "url": "http://www.reddit.com/r/LifeProTips/comments/2hnsck/lpt_study_a_map_of_a_different_place_in_the_world/", 
            "author": "intergalacticist", 
            "permalink": "http://www.reddit.com/r/LifeProTips/comments/2hnsck/lpt_study_a_map_of_a_different_place_in_the_world/", 
            "created-utc": 1411865425.0, 
            "id": "2hnsck"
        }, 
        {
            "num-comments": 4, 
            "domain": "self.LifeProTips", 
            "score": 13, 
            "nsfw": false, 
            "title": "LPT Request: Networking in College", 
            "url": "http://www.reddit.com/r/LifeProTips/comments/2hpusq/lpt_request_networking_in_college/", 
            "author": "juicedtapestry", 
            "permalink": "http://www.reddit.com/r/LifeProTips/comments/2hpusq/lpt_request_networking_in_college/", 
            "created-utc": 1411930316.0, 
            "id": "2hpusq"
        }, 
        {
            "num-comments": 7, 
            "domain": "self.LifeProTips", 
            "score": 3, 
            "nsfw": false, 
            "title": "LPT request: What to do about my hair shedding in the shower?", 
            "url": "http://www.reddit.com/r/LifeProTips/comments/2hq0nu/lpt_request_what_to_do_about_my_hair_shedding_in/", 
            "author": "TheRealGodzilla", 
            "permalink": "http://www.reddit.com/r/LifeProTips/comments/2hq0nu/lpt_request_what_to_do_about_my_hair_shedding_in/", 
            "created-utc": 1411933714.0, 
            "id": "2hq0nu"
        }, 
        {
            "num-comments": 0, 
            "domain": "self.LifeProTips", 
            "score": 2, 
            "nsfw": false, 
            "title": "LPT: When not sure if the spell check is working, or not picking up an incorrectly used word, right-click for synonyms to quickly confirm the word.", 
            "url": "http://www.reddit.com/r/LifeProTips/comments/2hpzgf/lpt_when_not_sure_if_the_spell_check_is_working/", 
            "author": "smw5412", 
            "permalink": "http://www.reddit.com/r/LifeProTips/comments/2hpzgf/lpt_when_not_sure_if_the_spell_check_is_working/", 
            "created-utc": 1411933026.0, 
            "id": "2hpzgf"
        }, 
        {
            "num-comments": 6, 
            "domain": "self.LifeProTips", 
            "score": 2, 
            "nsfw": false, 
            "title": "[LPT Request] My first ever solo long flight with a lay-over. Any tips?", 
            "url": "http://www.reddit.com/r/LifeProTips/comments/2hpuac/lpt_request_my_first_ever_solo_long_flight_with_a/", 
            "author": "second_shadow", 
            "permalink": "http://www.reddit.com/r/LifeProTips/comments/2hpuac/lpt_request_my_first_ever_solo_long_flight_with_a/", 
            "created-utc": 1411930030.0, 
            "id": "2hpuac"
        }, 
        {
            "num-comments": 5, 
            "domain": "self.LifeProTips", 
            "score": 0, 
            "nsfw": false, 
            "title": "LPT: Reheat leftover pizza in a toaster oven or regular oven at 400 \u00b0F for 4-5 minutes (until cheese is melted).", 
            "url": "http://www.reddit.com/r/LifeProTips/comments/2hpy6f/lpt_reheat_leftover_pizza_in_a_toaster_oven_or/", 
            "author": "Snatchary", 
            "permalink": "http://www.reddit.com/r/LifeProTips/comments/2hpy6f/lpt_reheat_leftover_pizza_in_a_toaster_oven_or/", 
            "created-utc": 1411932313.0, 
            "id": "2hpy6f"
        }, 
        {
            "num-comments": 7, 
            "domain": "self.LifeProTips", 
            "score": 0, 
            "nsfw": false, 
            "title": "LPT: Put a wooden spoon across the top of a boiling pot to keep it from boiling over", 
            "url": "http://www.reddit.com/r/LifeProTips/comments/2hpch1/lpt_put_a_wooden_spoon_across_the_top_of_a/", 
            "author": "ChooseWisely72", 
            "permalink": "http://www.reddit.com/r/LifeProTips/comments/2hpch1/lpt_put_a_wooden_spoon_across_the_top_of_a/", 
            "created-utc": 1411919148.0, 
            "id": "2hpch1"
        }, 
        {
            "num-comments": 9, 
            "domain": "self.LifeProTips", 
            "score": 0, 
            "nsfw": false, 
            "title": "LPT: The side of the USB with the line goes on the bottom.", 
            "url": "http://www.reddit.com/r/LifeProTips/comments/2hpj62/lpt_the_side_of_the_usb_with_the_line_goes_on_the/", 
            "author": "InsaneZee", 
            "permalink": "http://www.reddit.com/r/LifeProTips/comments/2hpj62/lpt_the_side_of_the_usb_with_the_line_goes_on_the/", 
            "created-utc": 1411923336.0, 
            "id": "2hpj62"
        }, 
        {
            "num-comments": 4, 
            "domain": "self.LifeProTips", 
            "score": 0, 
            "nsfw": false, 
            "title": "LPT: Use a pad of sticky notes instead of a coaster", 
            "url": "http://www.reddit.com/r/LifeProTips/comments/2hpsak/lpt_use_a_pad_of_sticky_notes_instead_of_a_coaster/", 
            "author": "ironicsh", 
            "permalink": "http://www.reddit.com/r/LifeProTips/comments/2hpsak/lpt_use_a_pad_of_sticky_notes_instead_of_a_coaster/", 
            "created-utc": 1411928838.0, 
            "id": "2hpsak"
        }, 
        {
            "num-comments": 21, 
            "domain": "self.LifeProTips", 
            "score": 0, 
            "nsfw": false, 
            "title": "LPT request : when I get drunk I forget where I live, what should I do?", 
            "url": "http://www.reddit.com/r/LifeProTips/comments/2hpkjo/lpt_request_when_i_get_drunk_i_forget_where_i/", 
            "author": "coriacea", 
            "permalink": "http://www.reddit.com/r/LifeProTips/comments/2hpkjo/lpt_request_when_i_get_drunk_i_forget_where_i/", 
            "created-utc": 1411924169.0, 
            "id": "2hpkjo"
        }, 
        {
            "num-comments": 4, 
            "domain": "self.LifeProTips", 
            "score": 0, 
            "nsfw": false, 
            "title": "LPT for Mac users. If you close a browser tab by mistake, reopen it by typing command+shift+t", 
            "url": "http://www.reddit.com/r/LifeProTips/comments/2hom6k/lpt_for_mac_users_if_you_close_a_browser_tab_by/", 
            "author": "darryljenks", 
            "permalink": "http://www.reddit.com/r/LifeProTips/comments/2hom6k/lpt_for_mac_users_if_you_close_a_browser_tab_by/", 
            "created-utc": 1411891759.0, 
            "id": "2hom6k"
        }, 
        {
            "num-comments": 2, 
            "domain": "self.LifeProTips", 
            "score": 0, 
            "nsfw": false, 
            "title": "LPT: remembering friends SO's name.", 
            "url": "http://www.reddit.com/r/LifeProTips/comments/2ho9z6/lpt_remembering_friends_sos_name/", 
            "author": "jeyenne", 
            "permalink": "http://www.reddit.com/r/LifeProTips/comments/2ho9z6/lpt_remembering_friends_sos_name/", 
            "created-utc": 1411878820.0, 
            "id": "2ho9z6"
        }, 
        {
            "num-comments": 5, 
            "domain": "self.LifeProTips", 
            "score": 0, 
            "nsfw": false, 
            "title": "LPT: Never get caught doing anything wrong again.", 
            "url": "http://www.reddit.com/r/LifeProTips/comments/2hobjm/lpt_never_get_caught_doing_anything_wrong_again/", 
            "author": "adrianmakedonski", 
            "permalink": "http://www.reddit.com/r/LifeProTips/comments/2hobjm/lpt_never_get_caught_doing_anything_wrong_again/", 
            "created-utc": 1411880209.0, 
            "id": "2hobjm"
        }, 
        {
            "num-comments": 0, 
            "domain": "self.LifeProTips", 
            "score": 0, 
            "nsfw": false, 
            "title": "LPT: You are not a conditioned dog.", 
            "url": "http://www.reddit.com/r/LifeProTips/comments/2ho91u/lpt_you_are_not_a_conditioned_dog/", 
            "author": "xenxah", 
            "permalink": "http://www.reddit.com/r/LifeProTips/comments/2ho91u/lpt_you_are_not_a_conditioned_dog/", 
            "created-utc": 1411878047.0, 
            "id": "2ho91u"
        }
    ], 
    "reddit-url": "http://www.reddit.com/r/LifeProTips/", 
    "api-url": "http://daily.red/life-pro-tips.json", 
    "display-name": "Life Pro Tips"
}