{
    "description": "A place to read and share positive and uplifting, feel good news stories", 
    "title": "Uplifting News", 
    "generated-utc": 1412373632, 
    "posts": [
        {
            "permalink": "http://www.reddit.com/r/UpliftingNews/comments/2i5njg/man_is_getting_coffee_with_all_1088_of_his/", 
            "domain": "inspiremore.com", 
            "score": 1173, 
            "nsfw": false, 
            "author": "IronMan4343", 
            "url": "http://inspiremore.com/this-guy-has-a-mission-to-get-to-know-each-and-every-one-of-his-facebook-friends-all-1088-of-them/", 
            "title": "Man is getting coffee with all 1,088 of his Facebook friends to get to know them better in person.", 
            "id": "2i5njg", 
            "created-utc": 1412306452.0, 
            "num-comments": 173
        }, 
        {
            "permalink": "http://www.reddit.com/r/UpliftingNews/comments/2i4hdi/quadriplegic_texas_woman_defies_odds_walks_and/", 
            "domain": "gma.yahoo.com", 
            "score": 721, 
            "nsfw": false, 
            "author": "menmybabies", 
            "url": "https://gma.yahoo.com/quadriplegic-texas-woman-defies-odds-walks-becomes-pregnant-130434683.html", 
            "title": "Quadriplegic Texas Woman Defies Odds, Walks and Becomes Pregnant", 
            "id": "2i4hdi", 
            "created-utc": 1412281693.0, 
            "num-comments": 107
        }, 
        {
            "permalink": "http://www.reddit.com/r/UpliftingNews/comments/2i4lrb/pizza_hut_giving_away_free_pizza_to_adults_who/", 
            "domain": "dailydot.com", 
            "score": 238, 
            "nsfw": false, 
            "author": "holyfruits", 
            "url": "http://www.dailydot.com/geek/book-it-back-adults-pizza-hut/", 
            "title": "Pizza Hut giving away free pizza to adults who participated in their reading incentive program Book It!", 
            "id": "2i4lrb", 
            "created-utc": 1412283960.0, 
            "num-comments": 16
        }, 
        {
            "permalink": "http://www.reddit.com/r/UpliftingNews/comments/2i6uxp/my_greatgrandmother_is_turning_100_in_10_days_i/", 
            "domain": "i.imgur.com", 
            "score": 1002, 
            "nsfw": false, 
            "author": "bengarisson", 
            "url": "http://i.imgur.com/TlorbHc.jpg?", 
            "title": "My greatgrandmother is turning 100 in 10 days. I didn't know where to post this, but I think UpliftingNews would care!", 
            "id": "2i6uxp", 
            "created-utc": 1412346423.0, 
            "num-comments": 104
        }, 
        {
            "permalink": "http://www.reddit.com/r/UpliftingNews/comments/2i6and/mike_tyson_will_be_speaking_to_students_in/", 
            "domain": "mantecabulletin.com", 
            "score": 30, 
            "nsfw": false, 
            "author": "Cellartech", 
            "url": "http://www.mantecabulletin.com/section/42/article/115750/", 
            "title": "Mike Tyson will be speaking to students in Manteca, CA today. Tyson is expected to discuss the importance of decision making at a young age and the long-term effects those decisions can have.", 
            "id": "2i6and", 
            "created-utc": 1412328199.0, 
            "num-comments": 14
        }, 
        {
            "permalink": "http://www.reddit.com/r/UpliftingNews/comments/2i4awc/us_high_school_dropout_rate_reaches_record_low/", 
            "domain": "pewresearch.org", 
            "score": 26, 
            "nsfw": false, 
            "author": "r_d_olivaw", 
            "url": "http://www.pewresearch.org/fact-tank/2014/10/02/u-s-high-school-dropout-rate-reaches-record-low-driven-by-improvements-among-hispanics-blacks/", 
            "title": "U.S. high school dropout rate reaches record low", 
            "id": "2i4awc", 
            "created-utc": 1412278275.0, 
            "num-comments": 3
        }, 
        {
            "permalink": "http://www.reddit.com/r/UpliftingNews/comments/2i56z6/paralyzed_bride_walks_down_the_aisle_during_her/", 
            "domain": "ktvu.com", 
            "score": 8, 
            "nsfw": false, 
            "author": "SaviorH", 
            "url": "http://www.ktvu.com/news/lifestyles/weddings/paralyzed-bride-amazes-everyone-walking-down-aisle/nhZzJ/", 
            "title": "Paralyzed Bride walks down the aisle during her wedding", 
            "id": "2i56z6", 
            "created-utc": 1412296193.0, 
            "num-comments": 1
        }, 
        {
            "permalink": "http://www.reddit.com/r/UpliftingNews/comments/2i6gx8/gaming_charity_going_all_out_to_help_sick_kids/", 
            "domain": "ocregister.com", 
            "score": 9, 
            "nsfw": false, 
            "author": "ShetlandJames", 
            "url": "http://www.ocregister.com/articles/well-637053-gamers-sharpe.html", 
            "title": "Gaming charity going all out to help sick kids and seniors", 
            "id": "2i6gx8", 
            "created-utc": 1412335591.0, 
            "num-comments": 3
        }, 
        {
            "permalink": "http://www.reddit.com/r/UpliftingNews/comments/2i4i8j/rescuing_hazel_grace_from_a_torturous_life/", 
            "domain": "lifewithdogs.tv", 
            "score": 7, 
            "nsfw": false, 
            "author": "menmybabies", 
            "url": "http://www.lifewithdogs.tv/2014/10/rescuing-hazel-grace-from-a-torturous-life/", 
            "title": "Rescuing Hazel Grace from a torturous life", 
            "id": "2i4i8j", 
            "created-utc": 1412282117.0, 
            "num-comments": 0
        }, 
        {
            "permalink": "http://www.reddit.com/r/UpliftingNews/comments/2i4hf7/after_lemonade_stand_robbery_community_and_famous/", 
            "domain": "gma.yahoo.com", 
            "score": 5, 
            "nsfw": false, 
            "author": "menmybabies", 
            "url": "https://gma.yahoo.com/lemonade-stand-robbery-community-famous-author-rally-help-143438562.html", 
            "title": "After Lemonade Stand Robbery, Community and Famous Author Rally to Help Boy", 
            "id": "2i4hf7", 
            "created-utc": 1412281720.0, 
            "num-comments": 0
        }, 
        {
            "permalink": "http://www.reddit.com/r/UpliftingNews/comments/2i7jxd/84_year_old_retired_math_teacher_has_spent_the/", 
            "domain": "mapachili.com", 
            "score": 12, 
            "nsfw": false, 
            "author": "teamdelicious", 
            "url": "http://www.mapachili.com/?p=1723", 
            "title": "84 year old retired math teacher has spent the past 50 years recording audiobooks to help the blind.", 
            "id": "2i7jxd", 
            "created-utc": 1412360344.0, 
            "num-comments": 1
        }, 
        {
            "permalink": "http://www.reddit.com/r/UpliftingNews/comments/2i7cck/happy_world_smile_day/", 
            "domain": "biography.com", 
            "score": 4, 
            "nsfw": false, 
            "author": "LordNero", 
            "url": "http://www.biography.com/news/world-smile-day-photos", 
            "title": "Happy World Smile Day!", 
            "id": "2i7cck", 
            "created-utc": 1412356258.0, 
            "num-comments": 0
        }, 
        {
            "permalink": "http://www.reddit.com/r/UpliftingNews/comments/2i63j7/how_one_pair_of_glasses_can_make_a_difference_to/", 
            "domain": "nbcnews.com", 
            "score": 4, 
            "nsfw": false, 
            "author": "brotogeris1", 
            "url": "http://www.nbcnews.com/feature/making-a-difference/how-one-pair-glasses-can-make-difference-many-n217111", 
            "title": "How One Pair of Glasses Can Make a Difference to Many", 
            "id": "2i63j7", 
            "created-utc": 1412319854.0, 
            "num-comments": 0
        }, 
        {
            "permalink": "http://www.reddit.com/r/UpliftingNews/comments/2i5ryh/woman_has_epic_reaction_to_discovering_shes/", 
            "domain": "blogs.babycenter.com", 
            "score": 3, 
            "nsfw": false, 
            "author": "StenciledOut", 
            "url": "http://blogs.babycenter.com/mom_stories/photos-pregnancy-ivf-09302014-gardner-babies/", 
            "title": "Woman has epic reaction to discovering she's pregnant with quadruplets after long infertility battle", 
            "id": "2i5ryh", 
            "created-utc": 1412309541.0, 
            "num-comments": 0
        }, 
        {
            "permalink": "http://www.reddit.com/r/UpliftingNews/comments/2i4i38/lucy_formerly_paralyzed_dog_walks_again/", 
            "domain": "lifewithdogs.tv", 
            "score": 5, 
            "nsfw": false, 
            "author": "menmybabies", 
            "url": "http://www.lifewithdogs.tv/2014/10/1-lucy-formerly-paralyzed-dog-walks-again/", 
            "title": "Lucy: formerly paralyzed dog walks again", 
            "id": "2i4i38", 
            "created-utc": 1412282040.0, 
            "num-comments": 0
        }, 
        {
            "permalink": "http://www.reddit.com/r/UpliftingNews/comments/2i7l18/in_rare_alliance_shiites_join_sunnis_to_defend/", 
            "domain": "reuters.com", 
            "score": 18, 
            "nsfw": false, 
            "author": "Plowbeast", 
            "url": "http://www.reuters.com/article/2014/10/03/us-mideast-crisis-iraq-dhuluiya-insight-idUSKCN0HS0RE20141003", 
            "title": "In rare alliance, Shi'ites join Sunnis to defend Iraqi towns", 
            "id": "2i7l18", 
            "created-utc": 1412360956.0, 
            "num-comments": 1
        }, 
        {
            "permalink": "http://www.reddit.com/r/UpliftingNews/comments/2i6btw/how_smartphone_and_bluetooth_data_can_be_used_to/", 
            "domain": "software.ac.uk", 
            "score": 3, 
            "nsfw": false, 
            "author": "DeathHamster1", 
            "url": "http://www.software.ac.uk/blog/2014-10-03-smartphones-improved-disease-spread-modelling", 
            "title": "How smartphone and Bluetooth data can be used to predict the spread of pandemics such as Ebola", 
            "id": "2i6btw", 
            "created-utc": 1412329588.0, 
            "num-comments": 0
        }, 
        {
            "permalink": "http://www.reddit.com/r/UpliftingNews/comments/2i7g11/the_age_of_personal_dna_storage_has_arrived/", 
            "domain": "timeslive.co.za", 
            "score": 3, 
            "nsfw": false, 
            "author": "News24x7Live", 
            "url": "http://www.timeslive.co.za/lifestyle/2014/10/01/the-age-of-personal-dna-storage-has-arrived", 
            "title": "The Age Of Personal DNA Storage Has Arrived", 
            "id": "2i7g11", 
            "created-utc": 1412358231.0, 
            "num-comments": 0
        }
    ], 
    "subreddit": "/r/UpliftingNews/", 
    "expires-utc": 1412431200, 
    "reddit-url": "http://www.reddit.com/r/UpliftingNews/", 
    "api-url": "http://daily.red/uplifting-news.json", 
    "display-name": "Uplifting News", 
    "order": 3
}