{
    "description": "Things that make you say \"What the F*ck\"", 
    "title": "WTF?!", 
    "generated-utc": 1412287307, 
    "posts": [
        {
            "permalink": "http://www.reddit.com/r/WTF/comments/2i35fe/my_friend_got_a_figurine_made_of_himself_what_a/", 
            "domain": "imgur.com", 
            "score": 4012, 
            "nsfw": true, 
            "author": "bjarmeister", 
            "url": "http://imgur.com/a/9C8pq", 
            "title": "My friend got a figurine made of himself. What a glorious time to be alive! [NSFW]", 
            "id": "2i35fe", 
            "created-utc": 1412255736.0, 
            "num-comments": 1559
        }, 
        {
            "permalink": "http://www.reddit.com/r/WTF/comments/2i11yz/two_female_teachers_at_destrehan_high_school_in/", 
            "domain": "wgno.com", 
            "score": 3034, 
            "nsfw": false, 
            "author": "blazedshaggy", 
            "url": "http://wgno.com/2014/10/01/police-destrehan-teachers-had-a-three-way-with-a-student/", 
            "title": "Two female teachers at Destrehan High School in Louisiana arrested for having three-way sex with 16 year old student.", 
            "id": "2i11yz", 
            "created-utc": 1412198021.0, 
            "num-comments": 2414
        }, 
        {
            "permalink": "http://www.reddit.com/r/WTF/comments/2i21cz/i_hit_my_head_on_a_lightbulb_in_my_attic_my/", 
            "domain": "i.imgur.com", 
            "score": 2647, 
            "nsfw": true, 
            "author": "epsd101", 
            "url": "http://i.imgur.com/WIfU2f5.jpg", 
            "title": "I hit my head on a lightbulb in my attic. My finace\u00e9 told me to never show anyone the photos.", 
            "id": "2i21cz", 
            "created-utc": 1412218353.0, 
            "num-comments": 582
        }, 
        {
            "permalink": "http://www.reddit.com/r/WTF/comments/2i1hk2/my_aunt_just_posted_this_on_facebook_only_damage/", 
            "domain": "i.imgur.com", 
            "score": 2496, 
            "nsfw": false, 
            "author": "sothisispermanence", 
            "url": "http://i.imgur.com/VK31X4K.png", 
            "title": "My aunt just posted this on Facebook. Only damage was to the AC unit", 
            "id": "2i1hk2", 
            "created-utc": 1412206637.0, 
            "num-comments": 176
        }, 
        {
            "permalink": "http://www.reddit.com/r/WTF/comments/2i2x4e/halloween_decoration/", 
            "domain": "i.imgur.com", 
            "score": 2574, 
            "nsfw": false, 
            "author": "MiittchXD", 
            "url": "http://i.imgur.com/V94owy2.jpg", 
            "title": "Halloween Decoration", 
            "id": "2i2x4e", 
            "created-utc": 1412248547.0, 
            "num-comments": 399
        }, 
        {
            "permalink": "http://www.reddit.com/r/WTF/comments/2i1ceb/the_hellish_scene_resulting_from_the_culling_and/", 
            "domain": "i.imgur.com", 
            "score": 2313, 
            "nsfw": false, 
            "author": "FabulousFlavor", 
            "url": "http://i.imgur.com/9rdJ2dS.jpg", 
            "title": "The hellish scene resulting from the culling and disposal (burning) of millions of animals infected by Foot and Mouth disease in the UK in 2001.", 
            "id": "2i1ceb", 
            "created-utc": 1412203667.0, 
            "num-comments": 215
        }, 
        {
            "permalink": "http://www.reddit.com/r/WTF/comments/2i2nk9/girlfriends_house_gets_raided_by_slugs/", 
            "domain": "i.imgur.com", 
            "score": 2297, 
            "nsfw": false, 
            "author": "subtlesparky", 
            "url": "http://i.imgur.com/yTP6wYM.jpg", 
            "title": "Girlfriends house gets raided by slugs!", 
            "id": "2i2nk9", 
            "created-utc": 1412236856.0, 
            "num-comments": 305
        }, 
        {
            "permalink": "http://www.reddit.com/r/WTF/comments/2i149u/the_innards_of_a_realistic_sex_doll/", 
            "domain": "imgur.com", 
            "score": 2134, 
            "nsfw": false, 
            "author": "kretik", 
            "url": "http://imgur.com/lR7er6m", 
            "title": "The innards of a realistic sex doll", 
            "id": "2i149u", 
            "created-utc": 1412199248.0, 
            "num-comments": 227
        }, 
        {
            "permalink": "http://www.reddit.com/r/WTF/comments/2i1xmv/all_i_wanted_was_an_omelet/", 
            "domain": "i.imgur.com", 
            "score": 1907, 
            "nsfw": true, 
            "author": "Wlpxx7", 
            "url": "http://i.imgur.com/1pJxd8K.jpg?1", 
            "title": "All I wanted was an omelet...", 
            "id": "2i1xmv", 
            "created-utc": 1412216200.0, 
            "num-comments": 354
        }, 
        {
            "permalink": "http://www.reddit.com/r/WTF/comments/2i1f5j/pretty_butterflies/", 
            "domain": "imgur.com", 
            "score": 1223, 
            "nsfw": false, 
            "author": "cnelsonsic", 
            "url": "http://imgur.com/hglbpcv", 
            "title": "Pretty Butterflies", 
            "id": "2i1f5j", 
            "created-utc": 1412205237.0, 
            "num-comments": 51
        }, 
        {
            "permalink": "http://www.reddit.com/r/WTF/comments/2i1uzr/smelled_something_rotting_in_the_hallway_by_my/", 
            "domain": "i.imgur.com", 
            "score": 883, 
            "nsfw": false, 
            "author": "ladyslovemybutt", 
            "url": "http://i.imgur.com/n7d3u8X.jpg", 
            "title": "Smelled something rotting in the hallway by my roommates room.", 
            "id": "2i1uzr", 
            "created-utc": 1412214559.0, 
            "num-comments": 194
        }, 
        {
            "permalink": "http://www.reddit.com/r/WTF/comments/2i2f7q/better_take_my_human_mask_off_dont_want_to/", 
            "domain": "i.imgur.com", 
            "score": 545, 
            "nsfw": false, 
            "author": "TomServoHere", 
            "url": "https://i.imgur.com/Ypn003s.jpg", 
            "title": "Better take my human mask off. Don't want to frighten anyone.", 
            "id": "2i2f7q", 
            "created-utc": 1412228263.0, 
            "num-comments": 32
        }, 
        {
            "permalink": "http://www.reddit.com/r/WTF/comments/2i341w/how_to_resuscitating_a_drowning_cat/", 
            "domain": "i.imgur.com", 
            "score": 487, 
            "nsfw": false, 
            "author": "Khusley", 
            "url": "http://i.imgur.com/Rqv79mI.jpg", 
            "title": "How to resuscitating a drowning cat", 
            "id": "2i341w", 
            "created-utc": 1412254754.0, 
            "num-comments": 90
        }, 
        {
            "permalink": "http://www.reddit.com/r/WTF/comments/2i41p4/rough_day_on_the_job_for_this_track_inspector/", 
            "domain": "giant.gfycat.com", 
            "score": 797, 
            "nsfw": false, 
            "author": "schlinker", 
            "url": "http://giant.gfycat.com/UncomfortableDeliciousHyracotherium.gif", 
            "title": "Rough day on the job for this track inspector", 
            "id": "2i41p4", 
            "created-utc": 1412273550.0, 
            "num-comments": 92
        }, 
        {
            "permalink": "http://www.reddit.com/r/WTF/comments/2i31zo/russian_car_thieves/", 
            "domain": "gfycat.com", 
            "score": 430, 
            "nsfw": false, 
            "author": "iammanic", 
            "url": "https://gfycat.com/LankyEverlastingGelding", 
            "title": "Russian car thieves", 
            "id": "2i31zo", 
            "created-utc": 1412253070.0, 
            "num-comments": 53
        }, 
        {
            "permalink": "http://www.reddit.com/r/WTF/comments/2i22qr/a_statue_of_satan_in_the_bolivian_mine_of_cerro/", 
            "domain": "i.imgur.com", 
            "score": 312, 
            "nsfw": false, 
            "author": "arowberry", 
            "url": "http://i.imgur.com/AT6MtSN.jpg", 
            "title": "A statue of Satan in the Bolivian mine of Cerro Rico", 
            "id": "2i22qr", 
            "created-utc": 1412219211.0, 
            "num-comments": 41
        }, 
        {
            "permalink": "http://www.reddit.com/r/WTF/comments/2i1dk1/daggering_is_a_form_of_dance_originating_from/", 
            "domain": "youtube.com", 
            "score": 293, 
            "nsfw": false, 
            "author": "metalupyourmax", 
            "url": "https://www.youtube.com/watch?v=bmXk8Ub75Z4", 
            "title": "Daggering is a form of dance originating from Jamaica. The dance incorporates dry sex and wrestling, and when combined with WWE commentary, makes for some very entertaining watching.", 
            "id": "2i1dk1", 
            "created-utc": 1412204305.0, 
            "num-comments": 56
        }, 
        {
            "permalink": "http://www.reddit.com/r/WTF/comments/2i2kyn/teenage_girl_has_been_mutilated_by_rivals_jealous/", 
            "domain": "couriermail.com.au", 
            "score": 173, 
            "nsfw": false, 
            "author": "abcdqwerty1234", 
            "url": "http://www.couriermail.com.au/news/world/teenage-girl-mutilated-by-rivals-jealous-of-her-beauty/story-fnihsmjt-1227077359667?sv=2117dbabe127f4f98760ecec941a5f12", 
            "title": "teenage girl has been mutilated by rivals jealous of her beauty who wanted to make her look like the horror movie character Chucky", 
            "id": "2i2kyn", 
            "created-utc": 1412234065.0, 
            "num-comments": 66
        }, 
        {
            "permalink": "http://www.reddit.com/r/WTF/comments/2i3g2d/locked_up_nsfw/", 
            "domain": "i.imgur.com", 
            "score": 201, 
            "nsfw": true, 
            "author": "bubblr", 
            "url": "http://i.imgur.com/IbM8HKI.jpg", 
            "title": "Locked up [NSFW]", 
            "id": "2i3g2d", 
            "created-utc": 1412262115.0, 
            "num-comments": 37
        }, 
        {
            "permalink": "http://www.reddit.com/r/WTF/comments/2i3soc/too_late_already_crapped_pants/", 
            "domain": "i.imgur.com", 
            "score": 262, 
            "nsfw": false, 
            "author": "blerrycat", 
            "url": "http://i.imgur.com/Ccq8pGd.jpg", 
            "title": "Too late, already crapped pants", 
            "id": "2i3soc", 
            "created-utc": 1412268935.0, 
            "num-comments": 28
        }, 
        {
            "permalink": "http://www.reddit.com/r/WTF/comments/2i202f/roommate_left_a_surprise_when_she_moved_out/", 
            "domain": "i.imgur.com", 
            "score": 154, 
            "nsfw": false, 
            "author": "joeydynamo", 
            "url": "http://i.imgur.com/XOPaZbB.jpg", 
            "title": "Roommate left a surprise when she moved out", 
            "id": "2i202f", 
            "created-utc": 1412217576.0, 
            "num-comments": 31
        }, 
        {
            "permalink": "http://www.reddit.com/r/WTF/comments/2i37po/the_african_cave_spider/", 
            "domain": "pbs.twimg.com", 
            "score": 140, 
            "nsfw": false, 
            "author": "A_Damn_Idiot", 
            "url": "https://pbs.twimg.com/media/BY5Gs4jIcAA49KW.jpg", 
            "title": "The African Cave Spider.", 
            "id": "2i37po", 
            "created-utc": 1412257318.0, 
            "num-comments": 56
        }, 
        {
            "permalink": "http://www.reddit.com/r/WTF/comments/2i2hk6/hippo_biopsy/", 
            "domain": "imgur.com", 
            "score": 106, 
            "nsfw": true, 
            "author": "theatre_of_pain", 
            "url": "http://imgur.com/ZlZJGNY", 
            "title": "Hippo biopsy", 
            "id": "2i2hk6", 
            "created-utc": 1412230533.0, 
            "num-comments": 45
        }, 
        {
            "permalink": "http://www.reddit.com/r/WTF/comments/2i1say/the_doors/", 
            "domain": "imgur.com", 
            "score": 107, 
            "nsfw": false, 
            "author": "wtftrollwhore", 
            "url": "http://imgur.com/K8fhSX4", 
            "title": "The Doors", 
            "id": "2i1say", 
            "created-utc": 1412212949.0, 
            "num-comments": 33
        }, 
        {
            "permalink": "http://www.reddit.com/r/WTF/comments/2i1d7y/wtfok_im_done_surfing_the_web_today_nsfw/", 
            "domain": "liveleak.com", 
            "score": 83, 
            "nsfw": true, 
            "author": "Vinnyk84", 
            "url": "http://www.liveleak.com/view?i=5da_1412167387", 
            "title": "WTF...Ok i'm done surfing the web today (nsfw)", 
            "id": "2i1d7y", 
            "created-utc": 1412204117.0, 
            "num-comments": 54
        }
    ], 
    "subreddit": "/r/WTF/", 
    "expires-utc": 1412344800, 
    "reddit-url": "http://www.reddit.com/r/WTF/", 
    "api-url": "http://daily.red/wtf.json", 
    "display-name": "WTF", 
    "order": 0
}